<Parameters xmlns_xsi="http://www.w3.org/2001/XMLSchema-instance">
	<Parameters>
		<Index>0</Index>
		<Parameter>000</Parameter>
		<Read_Write>RD_ON</Read_Write>
		<Units>U_NO</Units>
		<Min>0</Min>
		<Max>511</Max>
		<Default>158</Default>
		<Value>158</Value>
		<Calibration_value>0</Calibration_value>
		<Display_value>158</Display_value>
	</Parameters>
	<Parameters>
		<Index>1</Index>
		<Parameter>101</Parameter>
		<Read_Write>RD_ON</Read_Write>
		<Units>U_NO</Units>
		<Min>1</Min>
		<Max>4</Max>
		<Default>2</Default>
		<Value>2</Value>
		<Calibration_value>0</Calibration_value>
		<Display_value>2</Display_value>
	</Parameters>
	<Parameters>
		<Index>2</Index>
		<Parameter>928</Parameter>
		<Read_Write>RD_ON</Read_Write>
		<Units>U_NO</Units>
		<Min>0</Min>
		<Max>16777216</Max>
		<Default>16</Default>
		<Value>16</Value>
		<Calibration_value>0</Calibration_value>
		<Display_value>16</Display_value>
	</Parameters>
	<Parameters>
		<Index>3</Index>
		<Parameter>133</Parameter>
		<Read_Write>RD_WR</Read_Write>
		<Units>U_NO</Units>
		<Min>0</Min>
		<Max>63</Max>
		<Default>0</Default>
		<Value>0</Value>
		<Calibration_value>0</Calibration_value>
		<Display_value>0</Display_value>
	</Parameters>
	<Parameters>
		<Index>4</Index>
		<Parameter>090</Parameter>
		<Read_Write>RD_WR</Read_Write>
		<Units>U_NO</Units>
		<Min>0</Min>
		<Max>65535</Max>
		<Default>0</Default>
		<Value>0</Value>
		<Calibration_value>0</Calibration_value>
		<Display_value>0</Display_value>
	</Parameters>
	<Parameters>
		<Index>5</Index>
		<Parameter>092</Parameter>
		<Read_Write>RD_ON</Read_Write>
		<Units>U_NO</Units>
		<Min>0</Min>
		<Max>16777216</Max>
		<Default>2024</Default>
		<Value>2024</Value>
		<Calibration_value>0</Calibration_value>
		<Display_value>2024</Display_value>
	</Parameters>
	<Parameters>
		<Index>6</Index>
		<Parameter>838</Parameter>
		<Read_Write>RD_WR</Read_Write>
		<Units>U_DC2</Units>
		<Min>-1000</Min>
		<Max>1000</Max>
		<Default>0</Default>
		<Value>0</Value>
		<Calibration_value>0</Calibration_value>
		<Display_value>0</Display_value>
	</Parameters>
	<Parameters>
		<Index>7</Index>
		<Parameter>839</Parameter>
		<Read_Write>RD_WR</Read_Write>
		<Units>U_DC2</Units>
		<Min>-1000</Min>
		<Max>1000</Max>
		<Default>0</Default>
		<Value>0</Value>
		<Calibration_value>0</Calibration_value>
		<Display_value>0</Display_value>
	</Parameters>
	<Parameters>
		<Index>8</Index>
		<Parameter>104</Parameter>
		<Read_Write>RD_WR</Read_Write>
		<Units>U_NO</Units>
		<Min>1</Min>
		<Max>5</Max>
		<Default>1</Default>
		<Value>1</Value>
		<Calibration_value>0</Calibration_value>
		<Display_value>1</Display_value>
	</Parameters>
	<Parameters>
		<Index>9</Index>
		<Parameter>102</Parameter>
		<Read_Write>RD_WR</Read_Write>
		<Units>U_NO</Units>
		<Min>1</Min>
		<Max>3</Max>
		<Default>1</Default>
		<Value>1</Value>
		<Calibration_value>0</Calibration_value>
		<Display_value>1</Display_value>
	</Parameters>
	<Parameters>
		<Index>10</Index>
		<Parameter>105</Parameter>
		<Read_Write>RD_WR</Read_Write>
		<Units>U_MU</Units>
		<Min>0</Min>
		<Max>100</Max>
		<Default>8.0</Default>
		<Value>8.0</Value>
		<Calibration_value>0</Calibration_value>
		<Display_value>8.0</Display_value>
	</Parameters>
	<Parameters>
		<Index>11</Index>
		<Parameter>106</Parameter>
		<Read_Write>RD_WR</Read_Write>
		<Units>U_MU</Units>
		<Min>0.01</Min>
		<Max>100</Max>
		<Default>7.925</Default>
		<Value>7.925</Value>
		<Calibration_value>0</Calibration_value>
		<Display_value>7.925</Display_value>
	</Parameters>
	<Parameters>
		<Index>12</Index>
		<Parameter>107</Parameter>
		<Read_Write>RD_WR</Read_Write>
		<Units>U_MU</Units>
		<Min>0.05</Min>
		<Max>100</Max>
		<Default>0.075</Default>
		<Value>0.075</Value>
		<Calibration_value>0</Calibration_value>
		<Display_value>0.075</Display_value>
	</Parameters>
	<Parameters>
		<Index>13</Index>
		<Parameter>108</Parameter>
		<Read_Write>RD_WR</Read_Write>
		<Units>U_PC</Units>
		<Min>0</Min>
		<Max>100</Max>
		<Default>20</Default>
		<Value>20</Value>
		<Calibration_value>0</Calibration_value>
		<Display_value>20</Display_value>
	</Parameters>
	<Parameters>
		<Index>14</Index>
		<Parameter>851</Parameter>
		<Read_Write>RD_WR</Read_Write>
		<Units>U_MU</Units>
		<Min>-999</Min>
		<Max>999</Max>
		<Default>0</Default>
		<Value>0</Value>
		<Calibration_value>0</Calibration_value>
		<Display_value>0</Display_value>
	</Parameters>
	<Parameters>
		<Index>15</Index>
		<Parameter>940</Parameter>
		<Read_Write>RD_WR</Read_Write>
		<Units>U_NO</Units>
		<Min>0</Min>
		<Max>1E6</Max>
		<Default>0</Default>
		<Value>0</Value>
		<Calibration_value>0</Calibration_value>
		<Display_value>0</Display_value>
	</Parameters>
	<Parameters>
		<Index>16</Index>
		<Parameter>941</Parameter>
		<Read_Write>RD_ON</Read_Write>
		<Units>U_DDMMYY</Units>
		<Min>0</Min>
		<Max>999999</Max>
		<Default>0</Default>
		<Value>0</Value>
		<Calibration_value>0</Calibration_value>
		<Display_value>0</Display_value>
	</Parameters>
	<Parameters>
		<Index>17</Index>
		<Parameter>942</Parameter>
		<Read_Write>RD_ON</Read_Write>
		<Units>U_TIME</Units>
		<Min>0</Min>
		<Max>9999</Max>
		<Default>0</Default>
		<Value>0</Value>
		<Calibration_value>0</Calibration_value>
		<Display_value>0</Display_value>
	</Parameters>
	<Parameters>
		<Index>18</Index>
		<Parameter>943</Parameter>
		<Read_Write>RD_ON</Read_Write>
		<Units>U_MN</Units>
		<Min>0</Min>
		<Max>10E8</Max>
		<Default>0</Default>
		<Value>0</Value>
		<Calibration_value>0</Calibration_value>
		<Display_value>0</Display_value>
	</Parameters>
	<Parameters>
		<Index>19</Index>
		<Parameter>944</Parameter>
		<Read_Write>RD_ON</Read_Write>
		<Units>U_HR</Units>
		<Min>0</Min>
		<Max>3.4E38</Max>
		<Default>0</Default>
		<Value>0</Value>
		<Calibration_value>0</Calibration_value>
		<Display_value>0</Display_value>
	</Parameters>
	<Parameters>
		<Index>20</Index>
		<Parameter>100</Parameter>
		<Read_Write>RD_WR</Read_Write>
		<Units>U_NO</Units>
		<Min>1</Min>
		<Max>4</Max>
		<Default>2</Default>
		<Value>2</Value>
		<Calibration_value>0</Calibration_value>
		<Display_value>2</Display_value>
	</Parameters>
	<Parameters>
		<Index>21</Index>
		<Parameter>921</Parameter>
		<Read_Write>RD_WR</Read_Write>
		<Units>U_NO</Units>
		<Min>0</Min>
		<Max>1</Max>
		<Default>0</Default>
		<Value>0</Value>
		<Calibration_value>0</Calibration_value>
		<Display_value>0</Display_value>
	</Parameters>
	<Parameters>
		<Index>22</Index>
		<Parameter>922</Parameter>
		<Read_Write>RD_WR</Read_Write>
		<Units>U_NO</Units>
		<Min>0</Min>
		<Max>999999</Max>
		<Default>1997</Default>
		<Value>1997</Value>
		<Calibration_value>0</Calibration_value>
		<Display_value>1997</Display_value>
	</Parameters>
	<Parameters>
		<Index>23</Index>
		<Parameter>005</Parameter>
		<Read_Write>RD_WR</Read_Write>
		<Units>U_NO</Units>
		<Min>0</Min>
		<Max>1</Max>
		<Default>1</Default>
		<Value>1</Value>
		<Calibration_value>0</Calibration_value>
		<Display_value>1</Display_value>
	</Parameters>
	<Parameters>
		<Index>24</Index>
		<Parameter>006</Parameter>
		<Read_Write>RD_WR</Read_Write>
		<Units>U_NO</Units>
		<Min>0</Min>
		<Max>1</Max>
		<Default>0</Default>
		<Value>0</Value>
		<Calibration_value>0</Calibration_value>
		<Display_value>0</Display_value>
	</Parameters>
	<Parameters>
		<Index>25</Index>
		<Parameter>007</Parameter>
		<Read_Write>RD_ON</Read_Write>
		<Units>U_NO</Units>
		<Min>0</Min>
		<Max>65535</Max>
		<Default>3</Default>
		<Value>3</Value>
		<Calibration_value>0</Calibration_value>
		<Display_value>3</Display_value>
	</Parameters>
	<Parameters>
		<Index>26</Index>
		<Parameter>020</Parameter>
		<Read_Write>RD_WR</Read_Write>
		<Units>U_NO</Units>
		<Min>0</Min>
		<Max>4</Max>
		<Default>0</Default>
		<Value>0</Value>
		<Calibration_value>0</Calibration_value>
		<Display_value>0</Display_value>
	</Parameters>
	<Parameters>
		<Index>27</Index>
		<Parameter>021</Parameter>
		<Read_Write>RD_WR</Read_Write>
		<Units>U_MU</Units>
		<Min>0</Min>
		<Max>1E5</Max>
		<Default>0</Default>
		<Value>0</Value>
		<Calibration_value>0</Calibration_value>
		<Display_value>0</Display_value>
	</Parameters>
	<Parameters>
		<Index>28</Index>
		<Parameter>028</Parameter>
		<Read_Write>RD_WR</Read_Write>
		<Units>U_NO</Units>
		<Min>0</Min>
		<Max>3</Max>
		<Default>1</Default>
		<Value>1</Value>
		<Calibration_value>0</Calibration_value>
		<Display_value>1</Display_value>
	</Parameters>
	<Parameters>
		<Index>29</Index>
		<Parameter>035</Parameter>
		<Read_Write>RD_WR</Read_Write>
		<Units>U_NO</Units>
		<Min>0</Min>
		<Max>1</Max>
		<Default>1</Default>
		<Value>1</Value>
		<Calibration_value>0</Calibration_value>
		<Display_value>1</Display_value>
	</Parameters>
	<Parameters>
		<Index>30</Index>
		<Parameter>042</Parameter>
		<Read_Write>RD_WR</Read_Write>
		<Units>U_NO</Units>
		<Min>1</Min>
		<Max>8</Max>
		<Default>4</Default>
		<Value>4</Value>
		<Calibration_value>0</Calibration_value>
		<Display_value>4</Display_value>
	</Parameters>
	<Parameters>
		<Index>31</Index>
		<Parameter>043</Parameter>
		<Read_Write>RD_WR</Read_Write>
		<Units>U_MU</Units>
		<Min>0</Min>
		<Max>100</Max>
		<Default>5</Default>
		<Value>5</Value>
		<Calibration_value>0</Calibration_value>
		<Display_value>5</Display_value>
	</Parameters>
	<Parameters>
		<Index>32</Index>
		<Parameter>044</Parameter>
		<Read_Write>RD_WR</Read_Write>
		<Units>U_NO</Units>
		<Min>0</Min>
		<Max>100</Max>
		<Default>2</Default>
		<Value>2</Value>
		<Calibration_value>0</Calibration_value>
		<Display_value>2</Display_value>
	</Parameters>
	<Parameters>
		<Index>33</Index>
		<Parameter>045</Parameter>
		<Read_Write>RD_WR</Read_Write>
		<Units>U_NO</Units>
		<Min>1</Min>
		<Max>31</Max>
		<Default>16</Default>
		<Value>16</Value>
		<Calibration_value>0</Calibration_value>
		<Display_value>16</Display_value>
	</Parameters>
	<Parameters>
		<Index>34</Index>
		<Parameter>047</Parameter>
		<Read_Write>RD_WR</Read_Write>
		<Units>U_NO</Units>
		<Min>0</Min>
		<Max>99</Max>
		<Default>10</Default>
		<Value>10</Value>
		<Calibration_value>0</Calibration_value>
		<Display_value>10</Display_value>
	</Parameters>
	<Parameters>
		<Index>35</Index>
		<Parameter>049</Parameter>
		<Read_Write>RD_WR</Read_Write>
		<Units>U_PC</Units>
		<Min>0</Min>
		<Max>100</Max>
		<Default>40</Default>
		<Value>40</Value>
		<Calibration_value>0</Calibration_value>
		<Display_value>40</Display_value>
	</Parameters>
	<Parameters>
		<Index>36</Index>
		<Parameter>070</Parameter>
		<Read_Write>RD_WR</Read_Write>
		<Units>U_NO</Units>
		<Min>0</Min>
		<Max>2</Max>
		<Default>1</Default>
		<Value>1</Value>
		<Calibration_value>0</Calibration_value>
		<Display_value>1</Display_value>
	</Parameters>
	<Parameters>
		<Index>37</Index>
		<Parameter>067</Parameter>
		<Read_Write>RD_WR</Read_Write>
		<Units>U_NO</Units>
		<Min>1</Min>
		<Max>3</Max>
		<Default>1</Default>
		<Value>1</Value>
		<Calibration_value>0</Calibration_value>
		<Display_value>1</Display_value>
	</Parameters>
	<Parameters>
		<Index>38</Index>
		<Parameter>071</Parameter>
		<Read_Write>RD_WR</Read_Write>
		<Units>U_NO</Units>
		<Min>0</Min>
		<Max>1</Max>
		<Default>1</Default>
		<Value>1</Value>
		<Calibration_value>0</Calibration_value>
		<Display_value>1</Display_value>
	</Parameters>
	<Parameters>
		<Index>39</Index>
		<Parameter>085</Parameter>
		<Read_Write>RD_WR</Read_Write>
		<Units>U_NO</Units>
		<Min>0</Min>
		<Max>100</Max>
		<Default>0</Default>
		<Value>0</Value>
		<Calibration_value>0</Calibration_value>
		<Display_value>0</Display_value>
	</Parameters>
	<Parameters>
		<Index>40</Index>
		<Parameter>086</Parameter>
		<Read_Write>RD_WR</Read_Write>
		<Units>U_SE</Units>
		<Min>0</Min>
		<Max>50</Max>
		<Default>1</Default>
		<Value>1</Value>
		<Calibration_value>0</Calibration_value>
		<Display_value>1</Display_value>
	</Parameters>
	<Parameters>
		<Index>41</Index>
		<Parameter>087</Parameter>
		<Read_Write>RD_WR</Read_Write>
		<Units>U_MA</Units>
		<Min>3.8</Min>
		<Max>22</Max>
		<Default>12</Default>
		<Value>12</Value>
		<Calibration_value>0</Calibration_value>
		<Display_value>12</Display_value>
	</Parameters>
	<Parameters>
		<Index>42</Index>
		<Parameter>088</Parameter>
		<Read_Write>RD_WR</Read_Write>
		<Units>U_NO</Units>
		<Min>0</Min>
		<Max>1</Max>
		<Default>0</Default>
		<Value>0</Value>
		<Calibration_value>0</Calibration_value>
		<Display_value>0</Display_value>
	</Parameters>
	<Parameters>
		<Index>43</Index>
		<Parameter>093</Parameter>
		<Read_Write>RD_WR</Read_Write>
		<Units>U_NO</Units>
		<Min>0</Min>
		<Max>65535</Max>
		<Default>0</Default>
		<Value>0</Value>
		<Calibration_value>0</Calibration_value>
		<Display_value>0</Display_value>
	</Parameters>
	<Parameters>
		<Index>44</Index>
		<Parameter>109</Parameter>
		<Read_Write>RD_WR</Read_Write>
		<Units>U_MU</Units>
		<Min>0</Min>
		<Max>100.0</Max>
		<Default>0.02</Default>
		<Value>0.02</Value>
		<Calibration_value>0</Calibration_value>
		<Display_value>0.02</Display_value>
	</Parameters>
	<Parameters>
		<Index>45</Index>
		<Parameter>110</Parameter>
		<Read_Write>RD_WR</Read_Write>
		<Units>U_MV</Units>
		<Min>0</Min>
		<Max>1000</Max>
		<Default>1000</Default>
		<Value>1000</Value>
		<Calibration_value>0</Calibration_value>
		<Display_value>1000</Display_value>
	</Parameters>
	<Parameters>
		<Index>46</Index>
		<Parameter>111</Parameter>
		<Read_Write>RD_WR</Read_Write>
		<Units>U_MU</Units>
		<Min>0</Min>
		<Max>100.0</Max>
		<Default>0.05</Default>
		<Value>0.05</Value>
		<Calibration_value>0</Calibration_value>
		<Display_value>0.05</Display_value>
	</Parameters>
	<Parameters>
		<Index>47</Index>
		<Parameter>112</Parameter>
		<Read_Write>RD_WR</Read_Write>
		<Units>U_MV</Units>
		<Min>0</Min>
		<Max>1000</Max>
		<Default>500</Default>
		<Value>500</Value>
		<Calibration_value>0</Calibration_value>
		<Display_value>500</Display_value>
	</Parameters>
	<Parameters>
		<Index>48</Index>
		<Parameter>113</Parameter>
		<Read_Write>RD_WR</Read_Write>
		<Units>U_MU</Units>
		<Min>0</Min>
		<Max>100.0</Max>
		<Default>0.350</Default>
		<Value>0.350</Value>
		<Calibration_value>0</Calibration_value>
		<Display_value>0.350</Display_value>
	</Parameters>
	<Parameters>
		<Index>49</Index>
		<Parameter>114</Parameter>
		<Read_Write>RD_WR</Read_Write>
		<Units>U_MV</Units>
		<Min>0</Min>
		<Max>1000</Max>
		<Default>260</Default>
		<Value>260</Value>
		<Calibration_value>0</Calibration_value>
		<Display_value>260</Display_value>
	</Parameters>
	<Parameters>
		<Index>50</Index>
		<Parameter>115</Parameter>
		<Read_Write>RD_WR</Read_Write>
		<Units>U_MU</Units>
		<Min>0</Min>
		<Max>100.0</Max>
		<Default>0.83</Default>
		<Value>0.83</Value>
		<Calibration_value>0</Calibration_value>
		<Display_value>0.83</Display_value>
	</Parameters>
	<Parameters>
		<Index>51</Index>
		<Parameter>116</Parameter>
		<Read_Write>RD_WR</Read_Write>
		<Units>U_MV</Units>
		<Min>0</Min>
		<Max>1000</Max>
		<Default>190</Default>
		<Value>190</Value>
		<Calibration_value>0</Calibration_value>
		<Display_value>190</Display_value>
	</Parameters>
	<Parameters>
		<Index>52</Index>
		<Parameter>117</Parameter>
		<Read_Write>RD_WR</Read_Write>
		<Units>U_MU</Units>
		<Min>0</Min>
		<Max>100.0</Max>
		<Default>2</Default>
		<Value>2</Value>
		<Calibration_value>0</Calibration_value>
		<Display_value>2</Display_value>
	</Parameters>
	<Parameters>
		<Index>53</Index>
		<Parameter>118</Parameter>
		<Read_Write>RD_WR</Read_Write>
		<Units>U_MV</Units>
		<Min>0</Min>
		<Max>1000</Max>
		<Default>140</Default>
		<Value>140</Value>
		<Calibration_value>0</Calibration_value>
		<Display_value>140</Display_value>
	</Parameters>
	<Parameters>
		<Index>54</Index>
		<Parameter>119</Parameter>
		<Read_Write>RD_WR</Read_Write>
		<Units>U_MU</Units>
		<Min>0</Min>
		<Max>100.0</Max>
		<Default>3</Default>
		<Value>3</Value>
		<Calibration_value>0</Calibration_value>
		<Display_value>3</Display_value>
	</Parameters>
	<Parameters>
		<Index>55</Index>
		<Parameter>120</Parameter>
		<Read_Write>RD_WR</Read_Write>
		<Units>U_MV</Units>
		<Min>0</Min>
		<Max>1000</Max>
		<Default>110</Default>
		<Value>110</Value>
		<Calibration_value>0</Calibration_value>
		<Display_value>110</Display_value>
	</Parameters>
	<Parameters>
		<Index>56</Index>
		<Parameter>121</Parameter>
		<Read_Write>RD_WR</Read_Write>
		<Units>U_MU</Units>
		<Min>0</Min>
		<Max>100.0</Max>
		<Default>4</Default>
		<Value>4</Value>
		<Calibration_value>0</Calibration_value>
		<Display_value>4</Display_value>
	</Parameters>
	<Parameters>
		<Index>57</Index>
		<Parameter>122</Parameter>
		<Read_Write>RD_WR</Read_Write>
		<Units>U_MV</Units>
		<Min>0</Min>
		<Max>1000</Max>
		<Default>100</Default>
		<Value>100</Value>
		<Calibration_value>0</Calibration_value>
		<Display_value>100</Display_value>
	</Parameters>
	<Parameters>
		<Index>58</Index>
		<Parameter>123</Parameter>
		<Read_Write>RD_WR</Read_Write>
		<Units>U_MU</Units>
		<Min>0</Min>
		<Max>100.0</Max>
		<Default>5</Default>
		<Value>5</Value>
		<Calibration_value>0</Calibration_value>
		<Display_value>5</Display_value>
	</Parameters>
	<Parameters>
		<Index>59</Index>
		<Parameter>124</Parameter>
		<Read_Write>RD_WR</Read_Write>
		<Units>U_MV</Units>
		<Min>0</Min>
		<Max>1000</Max>
		<Default>100</Default>
		<Value>100</Value>
		<Calibration_value>0</Calibration_value>
		<Display_value>100</Display_value>
	</Parameters>
	<Parameters>
		<Index>60</Index>
		<Parameter>125</Parameter>
		<Read_Write>RD_WR</Read_Write>
		<Units>U_MU</Units>
		<Min>0</Min>
		<Max>100.0</Max>
		<Default>6</Default>
		<Value>6</Value>
		<Calibration_value>0</Calibration_value>
		<Display_value>6</Display_value>
	</Parameters>
	<Parameters>
		<Index>61</Index>
		<Parameter>126</Parameter>
		<Read_Write>RD_WR</Read_Write>
		<Units>U_MV</Units>
		<Min>0</Min>
		<Max>1000</Max>
		<Default>80</Default>
		<Value>80</Value>
		<Calibration_value>0</Calibration_value>
		<Display_value>80</Display_value>
	</Parameters>
	<Parameters>
		<Index>62</Index>
		<Parameter>127</Parameter>
		<Read_Write>RD_WR</Read_Write>
		<Units>U_MU</Units>
		<Min>0</Min>
		<Max>100.0</Max>
		<Default>7</Default>
		<Value>7</Value>
		<Calibration_value>0</Calibration_value>
		<Display_value>7</Display_value>
	</Parameters>
	<Parameters>
		<Index>63</Index>
		<Parameter>128</Parameter>
		<Read_Write>RD_WR</Read_Write>
		<Units>U_MV</Units>
		<Min>0</Min>
		<Max>1000</Max>
		<Default>80</Default>
		<Value>80</Value>
		<Calibration_value>0</Calibration_value>
		<Display_value>80</Display_value>
	</Parameters>
	<Parameters>
		<Index>64</Index>
		<Parameter>129</Parameter>
		<Read_Write>RD_WR</Read_Write>
		<Units>U_MU</Units>
		<Min>0</Min>
		<Max>100.0</Max>
		<Default>8</Default>
		<Value>8</Value>
		<Calibration_value>0</Calibration_value>
		<Display_value>8</Display_value>
	</Parameters>
	<Parameters>
		<Index>65</Index>
		<Parameter>130</Parameter>
		<Read_Write>RD_WR</Read_Write>
		<Units>U_MV</Units>
		<Min>0</Min>
		<Max>1000</Max>
		<Default>80</Default>
		<Value>80</Value>
		<Calibration_value>0</Calibration_value>
		<Display_value>80</Display_value>
	</Parameters>
	<Parameters>
		<Index>66</Index>
		<Parameter>131</Parameter>
		<Read_Write>RD_WR</Read_Write>
		<Units>U_MU</Units>
		<Min>0</Min>
		<Max>100.0</Max>
		<Default>9.6</Default>
		<Value>9.6</Value>
		<Calibration_value>0</Calibration_value>
		<Display_value>9.6</Display_value>
	</Parameters>
	<Parameters>
		<Index>67</Index>
		<Parameter>132</Parameter>
		<Read_Write>RD_WR</Read_Write>
		<Units>U_MV</Units>
		<Min>0</Min>
		<Max>1000</Max>
		<Default>80</Default>
		<Value>80</Value>
		<Calibration_value>0</Calibration_value>
		<Display_value>80</Display_value>
	</Parameters>
	<Parameters>
		<Index>68</Index>
		<Parameter>580</Parameter>
		<Read_Write>RD_WR</Read_Write>
		<Units>U_TP</Units>
		<Min>-50</Min>
		<Max>100</Max>
		<Default>100</Default>
		<Value>100</Value>
		<Calibration_value>0</Calibration_value>
		<Display_value>100</Display_value>
	</Parameters>
	<Parameters>
		<Index>69</Index>
		<Parameter>581</Parameter>
		<Read_Write>RD_WR</Read_Write>
		<Units>U_DDMMYY</Units>
		<Min>0</Min>
		<Max>999999</Max>
		<Default>0</Default>
		<Value>0</Value>
		<Calibration_value>0</Calibration_value>
		<Display_value>0</Display_value>
	</Parameters>
	<Parameters>
		<Index>70</Index>
		<Parameter>582</Parameter>
		<Read_Write>RD_WR</Read_Write>
		<Units>U_TIME</Units>
		<Min>0</Min>
		<Max>9999</Max>
		<Default>0</Default>
		<Value>0</Value>
		<Calibration_value>0</Calibration_value>
		<Display_value>0</Display_value>
	</Parameters>
	<Parameters>
		<Index>71</Index>
		<Parameter>583</Parameter>
		<Read_Write>RD_WR</Read_Write>
		<Units>U_TP</Units>
		<Min>-50</Min>
		<Max>100</Max>
		<Default>-50</Default>
		<Value>-50</Value>
		<Calibration_value>0</Calibration_value>
		<Display_value>-50</Display_value>
	</Parameters>
	<Parameters>
		<Index>72</Index>
		<Parameter>584</Parameter>
		<Read_Write>RD_WR</Read_Write>
		<Units>U_DDMMYY</Units>
		<Min>0</Min>
		<Max>999999</Max>
		<Default>0</Default>
		<Value>0</Value>
		<Calibration_value>0</Calibration_value>
		<Display_value>0</Display_value>
	</Parameters>
	<Parameters>
		<Index>73</Index>
		<Parameter>585</Parameter>
		<Read_Write>RD_WR</Read_Write>
		<Units>U_TIME</Units>
		<Min>0</Min>
		<Max>9999</Max>
		<Default>0</Default>
		<Value>0</Value>
		<Calibration_value>0</Calibration_value>
		<Display_value>0</Display_value>
	</Parameters>
	<Parameters>
		<Index>74</Index>
		<Parameter>586</Parameter>
		<Read_Write>RD_WR</Read_Write>
		<Units>U_TP</Units>
		<Min>-50</Min>
		<Max>100</Max>
		<Default>20</Default>
		<Value>20</Value>
		<Calibration_value>0</Calibration_value>
		<Display_value>20</Display_value>
	</Parameters>
	<Parameters>
		<Index>75</Index>
		<Parameter>605</Parameter>
		<Read_Write>RD_WR</Read_Write>
		<Units>U_NO</Units>
		<Min>0</Min>
		<Max>8</Max>
		<Default>3</Default>
		<Value>3</Value>
		<Calibration_value>0</Calibration_value>
		<Display_value>3</Display_value>
	</Parameters>
	<Parameters>
		<Index>76</Index>
		<Parameter>600</Parameter>
		<Read_Write>RD_WR</Read_Write>
		<Units>U_NO</Units>
		<Min>0</Min>
		<Max>12</Max>
		<Default>0</Default>
		<Value>0</Value>
		<Calibration_value>0</Calibration_value>
		<Display_value>0</Display_value>
	</Parameters>
	<Parameters>
		<Index>77</Index>
		<Parameter>601</Parameter>
		<Read_Write>RD_WR</Read_Write>
		<Units>U_MU</Units>
		<Min>0</Min>
		<Max>100E3</Max>
		<Default>0</Default>
		<Value>0</Value>
		<Calibration_value>0</Calibration_value>
		<Display_value>0</Display_value>
	</Parameters>
	<Parameters>
		<Index>78</Index>
		<Parameter>602</Parameter>
		<Read_Write>RD_WR</Read_Write>
		<Units>U_MU</Units>
		<Min>0</Min>
		<Max>100E3</Max>
		<Default>0</Default>
		<Value>0</Value>
		<Calibration_value>0</Calibration_value>
		<Display_value>0</Display_value>
	</Parameters>
	<Parameters>
		<Index>79</Index>
		<Parameter>603</Parameter>
		<Read_Write>RD_WR</Read_Write>
		<Units>U_MU</Units>
		<Min>0</Min>
		<Max>100E3</Max>
		<Default>0</Default>
		<Value>0</Value>
		<Calibration_value>0</Calibration_value>
		<Display_value>0</Display_value>
	</Parameters>
	<Parameters>
		<Index>80</Index>
		<Parameter>606</Parameter>
		<Read_Write>RD_WR</Read_Write>
		<Units>U_DC2</Units>
		<Min>0</Min>
		<Max>10E8</Max>
		<Default>1</Default>
		<Value>1</Value>
		<Calibration_value>0</Calibration_value>
		<Display_value>1</Display_value>
	</Parameters>
	<Parameters>
		<Index>81</Index>
		<Parameter>610</Parameter>
		<Read_Write>RD_WR</Read_Write>
		<Units>U_MU</Units>
		<Min>0</Min>
		<Max>10E6</Max>
		<Default>0</Default>
		<Value>0</Value>
		<Calibration_value>0</Calibration_value>
		<Display_value>0</Display_value>
	</Parameters>
	<Parameters>
		<Index>82</Index>
		<Parameter>611</Parameter>
		<Read_Write>RD_WR</Read_Write>
		<Units>U_VU</Units>
		<Min>0</Min>
		<Max>10E6</Max>
		<Default>0</Default>
		<Value>0</Value>
		<Calibration_value>0</Calibration_value>
		<Display_value>0</Display_value>
	</Parameters>
	<Parameters>
		<Index>83</Index>
		<Parameter>612</Parameter>
		<Read_Write>RD_WR</Read_Write>
		<Units>U_MU</Units>
		<Min>0</Min>
		<Max>10E6</Max>
		<Default>0</Default>
		<Value>0</Value>
		<Calibration_value>0</Calibration_value>
		<Display_value>0</Display_value>
	</Parameters>
	<Parameters>
		<Index>84</Index>
		<Parameter>613</Parameter>
		<Read_Write>RD_WR</Read_Write>
		<Units>U_VU</Units>
		<Min>0</Min>
		<Max>10E6</Max>
		<Default>0</Default>
		<Value>0</Value>
		<Calibration_value>0</Calibration_value>
		<Display_value>0</Display_value>
	</Parameters>
	<Parameters>
		<Index>85</Index>
		<Parameter>614</Parameter>
		<Read_Write>RD_WR</Read_Write>
		<Units>U_MU</Units>
		<Min>0</Min>
		<Max>10E6</Max>
		<Default>0</Default>
		<Value>0</Value>
		<Calibration_value>0</Calibration_value>
		<Display_value>0</Display_value>
	</Parameters>
	<Parameters>
		<Index>86</Index>
		<Parameter>615</Parameter>
		<Read_Write>RD_WR</Read_Write>
		<Units>U_VU</Units>
		<Min>0</Min>
		<Max>10E6</Max>
		<Default>0</Default>
		<Value>0</Value>
		<Calibration_value>0</Calibration_value>
		<Display_value>0</Display_value>
	</Parameters>
	<Parameters>
		<Index>87</Index>
		<Parameter>616</Parameter>
		<Read_Write>RD_WR</Read_Write>
		<Units>U_MU</Units>
		<Min>0</Min>
		<Max>10E6</Max>
		<Default>0</Default>
		<Value>0</Value>
		<Calibration_value>0</Calibration_value>
		<Display_value>0</Display_value>
	</Parameters>
	<Parameters>
		<Index>88</Index>
		<Parameter>617</Parameter>
		<Read_Write>RD_WR</Read_Write>
		<Units>U_VU</Units>
		<Min>0</Min>
		<Max>10E6</Max>
		<Default>0</Default>
		<Value>0</Value>
		<Calibration_value>0</Calibration_value>
		<Display_value>0</Display_value>
	</Parameters>
	<Parameters>
		<Index>89</Index>
		<Parameter>618</Parameter>
		<Read_Write>RD_WR</Read_Write>
		<Units>U_MU</Units>
		<Min>0</Min>
		<Max>10E6</Max>
		<Default>0</Default>
		<Value>0</Value>
		<Calibration_value>0</Calibration_value>
		<Display_value>0</Display_value>
	</Parameters>
	<Parameters>
		<Index>90</Index>
		<Parameter>619</Parameter>
		<Read_Write>RD_WR</Read_Write>
		<Units>U_VU</Units>
		<Min>0</Min>
		<Max>10E6</Max>
		<Default>0</Default>
		<Value>0</Value>
		<Calibration_value>0</Calibration_value>
		<Display_value>0</Display_value>
	</Parameters>
	<Parameters>
		<Index>91</Index>
		<Parameter>620</Parameter>
		<Read_Write>RD_WR</Read_Write>
		<Units>U_MU</Units>
		<Min>0</Min>
		<Max>10E6</Max>
		<Default>0</Default>
		<Value>0</Value>
		<Calibration_value>0</Calibration_value>
		<Display_value>0</Display_value>
	</Parameters>
	<Parameters>
		<Index>92</Index>
		<Parameter>621</Parameter>
		<Read_Write>RD_WR</Read_Write>
		<Units>U_VU</Units>
		<Min>0</Min>
		<Max>10E6</Max>
		<Default>0</Default>
		<Value>0</Value>
		<Calibration_value>0</Calibration_value>
		<Display_value>0</Display_value>
	</Parameters>
	<Parameters>
		<Index>93</Index>
		<Parameter>622</Parameter>
		<Read_Write>RD_WR</Read_Write>
		<Units>U_MU</Units>
		<Min>0</Min>
		<Max>10E6</Max>
		<Default>0</Default>
		<Value>0</Value>
		<Calibration_value>0</Calibration_value>
		<Display_value>0</Display_value>
	</Parameters>
	<Parameters>
		<Index>94</Index>
		<Parameter>623</Parameter>
		<Read_Write>RD_WR</Read_Write>
		<Units>U_VU</Units>
		<Min>0</Min>
		<Max>10E6</Max>
		<Default>0</Default>
		<Value>0</Value>
		<Calibration_value>0</Calibration_value>
		<Display_value>0</Display_value>
	</Parameters>
	<Parameters>
		<Index>95</Index>
		<Parameter>624</Parameter>
		<Read_Write>RD_WR</Read_Write>
		<Units>U_MU</Units>
		<Min>0</Min>
		<Max>10E6</Max>
		<Default>0</Default>
		<Value>0</Value>
		<Calibration_value>0</Calibration_value>
		<Display_value>0</Display_value>
	</Parameters>
	<Parameters>
		<Index>96</Index>
		<Parameter>625</Parameter>
		<Read_Write>RD_WR</Read_Write>
		<Units>U_VU</Units>
		<Min>0</Min>
		<Max>10E6</Max>
		<Default>0</Default>
		<Value>0</Value>
		<Calibration_value>0</Calibration_value>
		<Display_value>0</Display_value>
	</Parameters>
	<Parameters>
		<Index>97</Index>
		<Parameter>626</Parameter>
		<Read_Write>RD_WR</Read_Write>
		<Units>U_MU</Units>
		<Min>0</Min>
		<Max>10E6</Max>
		<Default>0</Default>
		<Value>0</Value>
		<Calibration_value>0</Calibration_value>
		<Display_value>0</Display_value>
	</Parameters>
	<Parameters>
		<Index>98</Index>
		<Parameter>627</Parameter>
		<Read_Write>RD_WR</Read_Write>
		<Units>U_VU</Units>
		<Min>0</Min>
		<Max>10E6</Max>
		<Default>0</Default>
		<Value>0</Value>
		<Calibration_value>0</Calibration_value>
		<Display_value>0</Display_value>
	</Parameters>
	<Parameters>
		<Index>99</Index>
		<Parameter>628</Parameter>
		<Read_Write>RD_WR</Read_Write>
		<Units>U_MU</Units>
		<Min>0</Min>
		<Max>10E6</Max>
		<Default>0</Default>
		<Value>0</Value>
		<Calibration_value>0</Calibration_value>
		<Display_value>0</Display_value>
	</Parameters>
	<Parameters>
		<Index>100</Index>
		<Parameter>629</Parameter>
		<Read_Write>RD_WR</Read_Write>
		<Units>U_VU</Units>
		<Min>0</Min>
		<Max>10E6</Max>
		<Default>0</Default>
		<Value>0</Value>
		<Calibration_value>0</Calibration_value>
		<Display_value>0</Display_value>
	</Parameters>
	<Parameters>
		<Index>101</Index>
		<Parameter>630</Parameter>
		<Read_Write>RD_WR</Read_Write>
		<Units>U_MU</Units>
		<Min>0</Min>
		<Max>10E6</Max>
		<Default>0</Default>
		<Value>0</Value>
		<Calibration_value>0</Calibration_value>
		<Display_value>0</Display_value>
	</Parameters>
	<Parameters>
		<Index>102</Index>
		<Parameter>631</Parameter>
		<Read_Write>RD_WR</Read_Write>
		<Units>U_VU</Units>
		<Min>0</Min>
		<Max>10E6</Max>
		<Default>0</Default>
		<Value>0</Value>
		<Calibration_value>0</Calibration_value>
		<Display_value>0</Display_value>
	</Parameters>
	<Parameters>
		<Index>103</Index>
		<Parameter>632</Parameter>
		<Read_Write>RD_WR</Read_Write>
		<Units>U_MU</Units>
		<Min>0</Min>
		<Max>10E6</Max>
		<Default>0</Default>
		<Value>0</Value>
		<Calibration_value>0</Calibration_value>
		<Display_value>0</Display_value>
	</Parameters>
	<Parameters>
		<Index>104</Index>
		<Parameter>633</Parameter>
		<Read_Write>RD_WR</Read_Write>
		<Units>U_VU</Units>
		<Min>0</Min>
		<Max>10E6</Max>
		<Default>0</Default>
		<Value>0</Value>
		<Calibration_value>0</Calibration_value>
		<Display_value>0</Display_value>
	</Parameters>
	<Parameters>
		<Index>105</Index>
		<Parameter>634</Parameter>
		<Read_Write>RD_WR</Read_Write>
		<Units>U_MU</Units>
		<Min>0</Min>
		<Max>10E6</Max>
		<Default>0</Default>
		<Value>0</Value>
		<Calibration_value>0</Calibration_value>
		<Display_value>0</Display_value>
	</Parameters>
	<Parameters>
		<Index>106</Index>
		<Parameter>635</Parameter>
		<Read_Write>RD_WR</Read_Write>
		<Units>U_VU</Units>
		<Min>0</Min>
		<Max>10E6</Max>
		<Default>0</Default>
		<Value>0</Value>
		<Calibration_value>0</Calibration_value>
		<Display_value>0</Display_value>
	</Parameters>
	<Parameters>
		<Index>107</Index>
		<Parameter>636</Parameter>
		<Read_Write>RD_WR</Read_Write>
		<Units>U_MU</Units>
		<Min>0</Min>
		<Max>10E6</Max>
		<Default>0</Default>
		<Value>0</Value>
		<Calibration_value>0</Calibration_value>
		<Display_value>0</Display_value>
	</Parameters>
	<Parameters>
		<Index>108</Index>
		<Parameter>637</Parameter>
		<Read_Write>RD_WR</Read_Write>
		<Units>U_VU</Units>
		<Min>0</Min>
		<Max>10E6</Max>
		<Default>0</Default>
		<Value>0</Value>
		<Calibration_value>0</Calibration_value>
		<Display_value>0</Display_value>
	</Parameters>
	<Parameters>
		<Index>109</Index>
		<Parameter>638</Parameter>
		<Read_Write>RD_WR</Read_Write>
		<Units>U_MU</Units>
		<Min>0</Min>
		<Max>10E6</Max>
		<Default>0</Default>
		<Value>0</Value>
		<Calibration_value>0</Calibration_value>
		<Display_value>0</Display_value>
	</Parameters>
	<Parameters>
		<Index>110</Index>
		<Parameter>639</Parameter>
		<Read_Write>RD_WR</Read_Write>
		<Units>U_VU</Units>
		<Min>0</Min>
		<Max>10E6</Max>
		<Default>0</Default>
		<Value>0</Value>
		<Calibration_value>0</Calibration_value>
		<Display_value>0</Display_value>
	</Parameters>
	<Parameters>
		<Index>111</Index>
		<Parameter>640</Parameter>
		<Read_Write>RD_WR</Read_Write>
		<Units>U_MU</Units>
		<Min>0</Min>
		<Max>10E6</Max>
		<Default>0</Default>
		<Value>0</Value>
		<Calibration_value>0</Calibration_value>
		<Display_value>0</Display_value>
	</Parameters>
	<Parameters>
		<Index>112</Index>
		<Parameter>641</Parameter>
		<Read_Write>RD_WR</Read_Write>
		<Units>U_VU</Units>
		<Min>0</Min>
		<Max>10E6</Max>
		<Default>0</Default>
		<Value>0</Value>
		<Calibration_value>0</Calibration_value>
		<Display_value>0</Display_value>
	</Parameters>
	<Parameters>
		<Index>113</Index>
		<Parameter>697</Parameter>
		<Read_Write>RD_ON</Read_Write>
		<Units>U_NO</Units>
		<Min>0</Min>
		<Max>16</Max>
		<Default>0</Default>
		<Value>0</Value>
		<Calibration_value>0</Calibration_value>
		<Display_value>0</Display_value>
	</Parameters>
	<Parameters>
		<Index>114</Index>
		<Parameter>604</Parameter>
		<Read_Write>RD_ON</Read_Write>
		<Units>U_MU</Units>
		<Min>0</Min>
		<Max>10E8</Max>
		<Default>0</Default>
		<Value>0</Value>
		<Calibration_value>0</Calibration_value>
		<Display_value>0</Display_value>
	</Parameters>
	<Parameters>
		<Index>115</Index>
		<Parameter>607</Parameter>
		<Read_Write>RD_ON</Read_Write>
		<Units>U_VU</Units>
		<Min>0</Min>
		<Max>10E8</Max>
		<Default>0</Default>
		<Value>0</Value>
		<Calibration_value>0</Calibration_value>
		<Display_value>0</Display_value>
	</Parameters>
	<Parameters>
		<Index>116</Index>
		<Parameter>645</Parameter>
		<Read_Write>RD_WR</Read_Write>
		<Units>U_NO</Units>
		<Min>0</Min>
		<Max>1</Max>
		<Default>0</Default>
		<Value>0</Value>
		<Calibration_value>0</Calibration_value>
		<Display_value>0</Display_value>
	</Parameters>
	<Parameters>
		<Index>117</Index>
		<Parameter>696</Parameter>
		<Read_Write>RD_WR</Read_Write>
		<Units>U_NO</Units>
		<Min>0</Min>
		<Max>1</Max>
		<Default>0</Default>
		<Value>0</Value>
		<Calibration_value>0</Calibration_value>
		<Display_value>0</Display_value>
	</Parameters>
	<Parameters>
		<Index>118</Index>
		<Parameter>808</Parameter>
		<Read_Write>RD_WR</Read_Write>
		<Units>U_NO</Units>
		<Min>1</Min>
		<Max>5</Max>
		<Default>1</Default>
		<Value>1</Value>
		<Calibration_value>0</Calibration_value>
		<Display_value>1</Display_value>
	</Parameters>
	<Parameters>
		<Index>119</Index>
		<Parameter>809</Parameter>
		<Read_Write>RD_WR</Read_Write>
		<Units>U_MN</Units>
		<Min>0</Min>
		<Max>1000</Max>
		<Default>2.0</Default>
		<Value>2.0</Value>
		<Calibration_value>0</Calibration_value>
		<Display_value>2.0</Display_value>
	</Parameters>
	<Parameters>
		<Index>120</Index>
		<Parameter>834</Parameter>
		<Read_Write>RD_WR</Read_Write>
		<Units>U_MU</Units>
		<Min>-100</Min>
		<Max>100</Max>
		<Default>0</Default>
		<Value>0</Value>
		<Calibration_value>0</Calibration_value>
		<Display_value>0</Display_value>
	</Parameters>
	<Parameters>
		<Index>121</Index>
		<Parameter>835</Parameter>
		<Read_Write>RD_WR</Read_Write>
		<Units>U_MU</Units>
		<Min>-100</Min>
		<Max>100</Max>
		<Default>7.925</Default>
		<Value>7.925</Value>
		<Calibration_value>0</Calibration_value>
		<Display_value>7.925</Display_value>
	</Parameters>
	<Parameters>
		<Index>122</Index>
		<Parameter>841</Parameter>
		<Read_Write>RD_WR</Read_Write>
		<Units>U_NO</Units>
		<Min>0</Min>
		<Max>99</Max>
		<Default>5</Default>
		<Value>5</Value>
		<Calibration_value>0</Calibration_value>
		<Display_value>5</Display_value>
	</Parameters>
	<Parameters>
		<Index>123</Index>
		<Parameter>852</Parameter>
		<Read_Write>RD_WR</Read_Write>
		<Units>U_NO</Units>
		<Min>1</Min>
		<Max>3</Max>
		<Default>1</Default>
		<Value>1</Value>
		<Calibration_value>0</Calibration_value>
		<Display_value>1</Display_value>
	</Parameters>
	<Parameters>
		<Index>124</Index>
		<Parameter>854</Parameter>
		<Read_Write>RD_WR</Read_Write>
		<Units>U_TP</Units>
		<Min>-40</Min>
		<Max>100</Max>
		<Default>20</Default>
		<Value>20</Value>
		<Calibration_value>0</Calibration_value>
		<Display_value>20</Display_value>
	</Parameters>
	<Parameters>
		<Index>125</Index>
		<Parameter>860</Parameter>
		<Read_Write>RD_WR</Read_Write>
		<Units>U_NO</Units>
		<Min>60</Min>
		<Max>240</Max>
		<Default>85</Default>
		<Value>85</Value>
		<Calibration_value>0</Calibration_value>
		<Display_value>85</Display_value>
	</Parameters>
	<Parameters>
		<Index>126</Index>
		<Parameter>870</Parameter>
		<Read_Write>RD_WR</Read_Write>
		<Units>U_MU</Units>
		<Min>0.01</Min>
		<Max>100</Max>
		<Default>10.0</Default>
		<Value>10.0</Value>
		<Calibration_value>0</Calibration_value>
		<Display_value>10.0</Display_value>
	</Parameters>
	<Parameters>
		<Index>127</Index>
		<Parameter>871</Parameter>
		<Read_Write>RD_WR</Read_Write>
		<Units>U_MU</Units>
		<Min>0.01</Min>
		<Max>100</Max>
		<Default>10.0</Default>
		<Value>10.0</Value>
		<Calibration_value>0</Calibration_value>
		<Display_value>10.0</Display_value>
	</Parameters>
	<Parameters>
		<Index>128</Index>
		<Parameter>881</Parameter>
		<Read_Write>RD_WR</Read_Write>
		<Units>U_MU</Units>
		<Min>0</Min>
		<Max>100</Max>
		<Default>0.15</Default>
		<Value>0.15</Value>
		<Calibration_value>0</Calibration_value>
		<Display_value>0.15</Display_value>
	</Parameters>
	<Parameters>
		<Index>129</Index>
		<Parameter>884</Parameter>
		<Read_Write>RD_WR</Read_Write>
		<Units>U_PC</Units>
		<Min>0</Min>
		<Max>100</Max>
		<Default>50</Default>
		<Value>50</Value>
		<Calibration_value>0</Calibration_value>
		<Display_value>50</Display_value>
	</Parameters>
	<Parameters>
		<Index>130</Index>
		<Parameter>905</Parameter>
		<Read_Write>RD_WR</Read_Write>
		<Units>U_MV</Units>
		<Min>0</Min>
		<Max>1000</Max>
		<Default>80</Default>
		<Value>80</Value>
		<Calibration_value>0</Calibration_value>
		<Display_value>80</Display_value>
	</Parameters>
	<Parameters>
		<Index>131</Index>
		<Parameter>906</Parameter>
		<Read_Write>RD_WR</Read_Write>
		<Units>U_MU</Units>
		<Min>0</Min>
		<Max>999</Max>
		<Default>0.050</Default>
		<Value>0.050</Value>
		<Calibration_value>0</Calibration_value>
		<Display_value>0.050</Display_value>
	</Parameters>
		<Parameters>
		<Index>132</Index>
		<Parameter>926</Parameter>
		<Read_Write>RD_ON</Read_Write>
		<Units>U_NO</Units>
		<Min>0</Min>
		<Max>1E6</Max>
		<Default>53</Default>
		<Value>53</Value>
		<Calibration_value>0</Calibration_value>
		<Display_value>53</Display_value>
	</Parameters>
	<Parameters>
		<Index>133</Index>
		<Parameter>927</Parameter>
		<Read_Write>RD_ON</Read_Write>
		<Units>U_NO</Units>
		<Min>0</Min>
		<Max>1E6</Max>
		<Default>0</Default>
		<Value>0</Value>
		<Calibration_value>0</Calibration_value>
		<Display_value>0</Display_value>
	</Parameters>
	<Parameters>
		<Index>134</Index>
		<Parameter>931</Parameter>
		<Read_Write>RD_WR</Read_Write>
		<Units>U_DDMMYY</Units>
		<Min>0</Min>
		<Max>999999</Max>
		<Default>000000</Default>
		<Value>000000</Value>
		<Calibration_value>0</Calibration_value>
		<Display_value>000000</Display_value>
	</Parameters>
	<Parameters>
		<Index>135</Index>
		<Parameter>932</Parameter>
		<Read_Write>RD_WR</Read_Write>
		<Units>U_TIME</Units>
		<Min>0</Min>
		<Max>9999</Max>
		<Default>0000</Default>
		<Value>0000</Value>
		<Calibration_value>0</Calibration_value>
		<Display_value>0000</Display_value>
	</Parameters>
	<Parameters>
		<Index>136</Index>
		<Parameter>950</Parameter>
		<Read_Write>RD_WR</Read_Write>
		<Units>U_NO</Units>
		<Min>0</Min>
		<Max>2</Max>
		<Default>2</Default>
		<Value>2</Value>
		<Calibration_value>0</Calibration_value>
		<Display_value>2</Display_value>
	</Parameters>
	<Parameters>
		<Index>137</Index>
		<Parameter>930</Parameter>
		<Read_Write>RD_WR</Read_Write>
		<Units>U_NO</Units>
		<Min>0</Min>
		<Max>1</Max>
		<Default>0</Default>
		<Value>0</Value>
		<Calibration_value>0</Calibration_value>
		<Display_value>0</Display_value>
	</Parameters>
	<Parameters>
		<Index>138</Index>
		<Parameter>933</Parameter>
		<Read_Write>RD_WR</Read_Write>
		<Units>U_NO</Units>
		<Min>1</Min>
		<Max>3</Max>
		<Default>1</Default>
		<Value>1</Value>
		<Calibration_value>0</Calibration_value>
		<Display_value>1</Display_value>
	</Parameters>
	<Parameters>
		<Index>139</Index>
		<Parameter>951</Parameter>
		<Read_Write>RD_WR</Read_Write>
		<Units>U_MU</Units>
		<Min>-18</Min>
		<Max>100</Max>
		<Default>0</Default>
		<Value>0</Value>
		<Calibration_value>0</Calibration_value>
		<Display_value>0</Display_value>
	</Parameters>
	<Parameters>
		<Index>140</Index>
		<Parameter>952</Parameter>
		<Read_Write>RD_WR</Read_Write>
		<Units>U_MU</Units>
		<Min>-18</Min>
		<Max>100</Max>
		<Default>100</Default>
		<Value>100</Value>
		<Calibration_value>0</Calibration_value>
		<Display_value>100</Display_value>
	</Parameters>
	<Parameters>
		<Index>141</Index>
		<Parameter>953</Parameter>
		<Read_Write>RD_WR</Read_Write>
		<Units>U_NO</Units>
		<Min>0</Min>
		<Max>3</Max>
		<Default>0</Default>
		<Value>0</Value>
		<Calibration_value>0</Calibration_value>
		<Display_value>0</Display_value>
	</Parameters>
	<Parameters>
		<Index>142</Index>
		<Parameter>234</Parameter>
		<Read_Write>RD_WR</Read_Write>
		<Units>U_NO</Units>
		<Min>0</Min>
		<Max>1</Max>
		<Default>1</Default>
		<Value>1</Value>
		<Calibration_value>0</Calibration_value>
		<Display_value>1</Display_value>
	</Parameters>
	<Parameters>
		<Index>143</Index>
		<Parameter>235</Parameter>
		<Read_Write>RD_WR</Read_Write>
		<Units>U_NO</Units>
		<Min>0</Min>
		<Max>4095</Max>
		<Default>2048</Default>
		<Value>2048</Value>
		<Calibration_value>0</Calibration_value>
		<Display_value>2048</Display_value>
	</Parameters>
	<Parameters>
		<Index>144</Index>
		<Parameter>236</Parameter>
		<Read_Write>RD_WR</Read_Write>
		<Units>U_NO</Units>
		<Min>0</Min>
		<Max>4095</Max>
		<Default>2048</Default>
		<Value>2048</Value>
		<Calibration_value>0</Calibration_value>
		<Display_value>2048</Display_value>
	</Parameters>
	<Parameters>
		<Index>145</Index>
		<Parameter>237</Parameter>
		<Read_Write>RD_WR</Read_Write>
		<Units>U_NO</Units>
		<Min>0</Min>
		<Max>4095</Max>
		<Default>1720</Default>
		<Value>1720</Value>
		<Calibration_value>0</Calibration_value>
		<Display_value>1720</Display_value>
	</Parameters>
	<Parameters>
		<Index>146</Index>
		<Parameter>238</Parameter>
		<Read_Write>RD_WR</Read_Write>
		<Units>U_NO</Units>
		<Min>0</Min>
		<Max>1</Max>
		<Default>0</Default>
		<Value>0</Value>
		<Calibration_value>0</Calibration_value>
		<Display_value>0</Display_value>
	</Parameters>
	<Parameters>
		<Index>147</Index>
		<Parameter>239</Parameter>
		<Read_Write>RD_WR</Read_Write>
		<Units>U_NO</Units>
		<Min>0</Min>
		<Max>100</Max>
		<Default>0</Default>
		<Value>0</Value>
		<Calibration_value>0</Calibration_value>
		<Display_value>0</Display_value>
	</Parameters>
	<Parameters>
		<Index>148</Index>
		<Parameter>240</Parameter>
		<Read_Write>RD_WR</Read_Write>
		<Units>U_NO</Units>
		<Min>0</Min>
		<Max>2</Max>
		<Default>0</Default>
		<Value>0</Value>
		<Calibration_value>0</Calibration_value>
		<Display_value>0</Display_value>
	</Parameters>
	<Parameters>
		<Index>149</Index>
		<Parameter>241</Parameter>
		<Read_Write>RD_WR</Read_Write>
		<Units>U_NO</Units>
		<Min>0</Min>
		<Max>7</Max>
		<Default>7</Default>
		<Value>7</Value>
		<Calibration_value>0</Calibration_value>
		<Display_value>7</Display_value>
	</Parameters>
	<Parameters>
		<Index>150</Index>
		<Parameter>242</Parameter>
		<Read_Write>RD_WR</Read_Write>
		<Units>U_NO</Units>
		<Min>0</Min>
		<Max>100</Max>
		<Default>50</Default>
		<Value>50</Value>
		<Calibration_value>0</Calibration_value>
		<Display_value>50</Display_value>
	</Parameters>
	<Parameters>
		<Index>151</Index>
		<Parameter>243</Parameter>
		<Read_Write>RD_WR</Read_Write>
		<Units>U_NO</Units>
		<Min>0</Min>
		<Max>100</Max>
		<Default>25</Default>
		<Value>25</Value>
		<Calibration_value>0</Calibration_value>
		<Display_value>25</Display_value>
	</Parameters>
	<Parameters>
		<Index>152</Index>
		<Parameter>244</Parameter>
		<Read_Write>RD_WR</Read_Write>
		<Units>U_NO</Units>
		<Min>1</Min>
		<Max>999999</Max>
		<Default>100</Default>
		<Value>100</Value>
		<Calibration_value>0</Calibration_value>
		<Display_value>100</Display_value>
	</Parameters>
	<Parameters>
		<Index>153</Index>
		<Parameter>245</Parameter>
		<Read_Write>RD_ON</Read_Write>
		<Units>U_NO</Units>
		<Min>-1000</Min>
		<Max>1000</Max>
		<Default>0</Default>
		<Value>0</Value>
		<Calibration_value>0</Calibration_value>
		<Display_value>0</Display_value>
	</Parameters>
	<Parameters>
		<Index>154</Index>
		<Parameter>246</Parameter>
		<Read_Write>RD_WR</Read_Write>
		<Units>U_NO</Units>
		<Min>1</Min>
		<Max>100</Max>
		<Default>25</Default>
		<Value>25</Value>
		<Calibration_value>0</Calibration_value>
		<Display_value>25</Display_value>
	</Parameters>
	<Parameters>
		<Index>155</Index>
		<Parameter>247</Parameter>
		<Read_Write>RD_WR</Read_Write>
		<Units>U_NO</Units>
		<Min>0</Min>
		<Max>1</Max>
		<Default>0</Default>
		<Value>0</Value>
		<Calibration_value>0</Calibration_value>
		<Display_value>0</Display_value>
	</Parameters>
	<Parameters>
		<Index>156</Index>
		<Parameter>248</Parameter>
		<Read_Write>RD_WR</Read_Write>
		<Units>U_MA</Units>
		<Min>3.8</Min>
		<Max>22</Max>
		<Default>20</Default>
		<Value>20</Value>
		<Calibration_value>0</Calibration_value>
		<Display_value>20</Display_value>
	</Parameters>
	<Parameters>
		<Index>157</Index>
		<Parameter>999</Parameter>
		<Read_Write>RD_ON</Read_Write>
		<Units>U_NO</Units>
		<Min>1E-38</Min>
		<Max>1E38</Max>
		<Default>0</Default>
		<Value>0</Value>
		<Calibration_value>0</Calibration_value>
		<Display_value>0</Display_value>
	</Parameters>
</Parameters>
